varseek/__init__.py
varseek/__main__.py
varseek/constants.py
varseek/main.py
varseek/varseek_build.py
varseek/varseek_clean.py
varseek/varseek_count.py
varseek/varseek_fastqpp.py
varseek/varseek_filter.py
varseek/varseek_info.py
varseek/varseek_ref.py
varseek/varseek_sim.py
varseek/varseek_summarize.py
varseek/utils/__init__.py
varseek/utils/logger_utils.py
varseek/utils/seq_utils.py
varseek/utils/varseek_build_utils.py
varseek/utils/varseek_clean_utils.py
varseek/utils/varseek_fastqpp_utils.py
varseek/utils/varseek_filter_utils.py
varseek/utils/varseek_info_utils.py
varseek/utils/varseek_sim_utils.py
varseek/utils/varseek_summarize_utils.py
varseek/utils/visualization_utils.py
varseek-0.1.1.dist-info/licenses/LICENSE
varseek-0.1.1.dist-info/METADATA
varseek-0.1.1.dist-info/WHEEL
varseek-0.1.1.dist-info/entry_points.txt
varseek-0.1.1.dist-info/top_level.txt
varseek-0.1.1.dist-info/RECORD
