Metadata-Version: 2.4
Name: varseek
Version: 0.1.1
Summary: Efficient variant screening of RNA-seq and DNA-seq data using k-mer-based alignment against a reference of known variants.
Author-email: Joseph Rich <josephrich98@gmail.com>
Maintainer-email: Joseph Rich <josephrich98@gmail.com>
License: BSD 2-Clause License
Project-URL: Homepage, https://github.com/pachterlab/varseek
Keywords: varseek,bioinformatics,variant-analysis,k-mer,RNA-seq,DNA-seq
Classifier: Environment :: Console
Classifier: Framework :: Jupyter
Classifier: Intended Audience :: Science/Research
Classifier: License :: OSI Approved :: BSD License
Classifier: Operating System :: OS Independent
Classifier: Programming Language :: Python :: 3.9
Classifier: Programming Language :: Python :: 3.10
Classifier: Programming Language :: Python :: 3.11
Classifier: Programming Language :: Python :: 3.12
Classifier: Topic :: Scientific/Engineering :: Bio-Informatics
Classifier: Topic :: Utilities
Requires-Python: >=3.9
License-File: LICENSE
Requires-Dist: numpy<2.0.0,>=1.26.4
Requires-Dist: pandas<2.0.0,>=1.5.3
Requires-Dist: matplotlib>=3.9.0
Requires-Dist: tqdm>=4.66.4
Requires-Dist: anndata>=0.8.0
Requires-Dist: kb-python>=0.29.3
Requires-Dist: gget>=0.29.1
Requires-Dist: scipy>=1.13.1
Requires-Dist: pyfastx>=2.1.0
Requires-Dist: pysam>=0.22.1
Requires-Dist: pyarrow>=19.0.1
Provides-Extra: dev
Requires-Dist: pytest>=7.0.0; extra == "dev"
Requires-Dist: black[jupyter]>=22.0.0; extra == "dev"
Requires-Dist: isort>=6.0.0; extra == "dev"
Requires-Dist: toml>=0.10.2; extra == "dev"
Requires-Dist: flake8>=7.0.0; extra == "dev"
Requires-Dist: bandit>=1.8.2; extra == "dev"
Requires-Dist: pympler>=1.1; extra == "dev"
Provides-Extra: analysis
Requires-Dist: nbval>=0.10.0; extra == "analysis"
Requires-Dist: nbdime>=4.0.2; extra == "analysis"
Requires-Dist: matplotlib-venn>=1.0.0; extra == "analysis"
Requires-Dist: ipython>=8.0.0; extra == "analysis"
Requires-Dist: goatools>=1.4.9; extra == "analysis"
Requires-Dist: multiqc>=1.25.1; extra == "analysis"
Requires-Dist: rich>=11.0.0; extra == "analysis"
Requires-Dist: kneed>=0.8.0; extra == "analysis"
Requires-Dist: scanpy>=1.10.4; extra == "analysis"
Requires-Dist: upsetplot>=0.9.0; extra == "analysis"
Requires-Dist: pykegg>=0.1.7; extra == "analysis"
Requires-Dist: cyvcf2>=0.31.1; extra == "analysis"
Requires-Dist: seaborn>=0.13.2; extra == "analysis"
Requires-Dist: adjustText>=1.3.0; extra == "analysis"
Dynamic: license-file
